lib64/libnanoarrow_static.a
lib64/libnanoarrow_shared.so
lib64/cmake/nanoarrow/nanoarrow-targets.cmake
lib64/cmake/nanoarrow/nanoarrow-config-version.cmake
lib64/cmake/nanoarrow/nanoarrow-targets-release.cmake
lib64/cmake/nanoarrow/nanoarrow-config.cmake
pantab-5.2.2.dist-info/WHEEL
pantab-5.2.2.dist-info/METADATA
pantab-5.2.2.dist-info/RECORD
pantab-5.2.2.dist-info/licenses/LICENSE.txt
include/nanoarrow/nanoarrow.h
include/nanoarrow/nanoarrow_config.h
include/nanoarrow/nanoarrow.hpp
include/nanoarrow/common/inline_buffer.h
include/nanoarrow/common/inline_types.h
include/nanoarrow/common/inline_array.h
include/nanoarrow/hpp/unique.hpp
include/nanoarrow/hpp/view.hpp
include/nanoarrow/hpp/buffer.hpp
include/nanoarrow/hpp/array_stream.hpp
include/nanoarrow/hpp/exception.hpp
include/nanoarrow/hpp/operators.hpp
pantab/CMakeLists.txt
pantab/reader.cpp
pantab/__init__.py
pantab/_reader.py
pantab/libpantab.pyi
pantab/writer.hpp
pantab/libpantab.cpython-312-x86_64-linux-gnu.so
pantab/_writer.py
pantab/_types.py
pantab/libtableauhyperapi.so
pantab/libpantab.cpp
pantab/writer.cpp
pantab/numeric_gen.hpp
pantab/reader.hpp
pantab/hyper/hyperd
