Metadata-Version: 2.2
Name: pantab
Version: 5.2.2
Summary: Converts pandas DataFrames into Tableau Hyper Extracts and back
Keywords: tableau,visualization,pandas,dataframe
Author-Email: Will Ayd <will_ayd@innobi.io>
License: BSD 3-Clause License
Classifier: Development Status :: 5 - Production/Stable
Classifier: Intended Audience :: Developers
Classifier: Topic :: Office/Business
Classifier: Programming Language :: Python :: 3.9
Classifier: Programming Language :: Python :: 3.10
Classifier: Programming Language :: Python :: 3.11
Classifier: Programming Language :: Python :: 3.12
Classifier: Programming Language :: Python :: 3.13
Project-URL: Source, https://github.com/innobi/pantab
Requires-Python: >=3.9
Requires-Dist: pyarrow>=14.0.0
Provides-Extra: dev
Requires-Dist: pytest; extra == "dev"
